nucflag/__init__.py
nucflag/config.py
nucflag/io.py
nucflag/main.py
nucflag/misassembly.py
nucflag/plot.py
nucflag/region.py
nucflag/utils.py
nucflag/classifier/classifier.py
nucflag/classifier/collapse.py
nucflag/classifier/common.py
nucflag/classifier/het.py
nucflag/classifier/misjoin.py
nucflag-0.3.8.dist-info/licenses/LICENSE
nucflag-0.3.8.dist-info/METADATA
nucflag-0.3.8.dist-info/WHEEL
nucflag-0.3.8.dist-info/entry_points.txt
nucflag-0.3.8.dist-info/top_level.txt
nucflag-0.3.8.dist-info/RECORD
