Metadata-Version: 2.4
Name: nucflag
Version: 0.3.8
Summary: NucFlag misassembly identifier.
Author-email: Keith Oshima <oshimak@pennmedicine.upenn.edu>, "Mitchell R. Vollger" <mrvollger@gmail.com>
License: MIT License
Project-URL: Homepage, https://github.com/logsdon-lab/NucFlag
Requires-Python: >=3.12
License-File: LICENSE
Requires-Dist: matplotlib>=3.8.3
Requires-Dist: numpy>=1.26.4
Requires-Dist: polars>=1.6.0
Requires-Dist: intervaltree>=3.1.0
Requires-Dist: pysam>=0.22.0
Requires-Dist: scipy>=1.12.0
Requires-Dist: pyBigWig>=0.3.24
Dynamic: license-file
